[
    {
        "id": "ee51f05b-c153-4536-8900-5d475768164c",
        "username": "amazon",
        "password": "p9ab8t6acV@#$bwaal",
        "email": "hiring@amazon.jobs",
        "firstName": "Amazon",
        "lastName": "Rep",
        "approved": true,
        "company": "Amazon"
    },
    {
        "id": "69599de1-4423-4573-b40d-145d290282e1",
        "username": "google",
        "password": "WE$%TVE$%^B&SE%VY",
        "email": "go@og.le",
        "firstName": "Hiring",
        "lastName": "Representative",
        "approved": false,
        "company": "Google"
    }
]